huaweicloudsdkedgesec/__init__.py
huaweicloudsdkedgesec/v2/__init__.py
huaweicloudsdkedgesec/v2/edgesec_async_client.py
huaweicloudsdkedgesec/v2/edgesec_client.py
huaweicloudsdkedgesec/v2/model/__init__.py
huaweicloudsdkedgesec/v2/model/apply_http_policy_request.py
huaweicloudsdkedgesec/v2/model/apply_http_policy_request_body.py
huaweicloudsdkedgesec/v2/model/apply_http_policy_response.py
huaweicloudsdkedgesec/v2/model/attack_type_classification_item.py
huaweicloudsdkedgesec/v2/model/attack_type_item.py
huaweicloudsdkedgesec/v2/model/common_stat_item.py
huaweicloudsdkedgesec/v2/model/create_domain_request.py
huaweicloudsdkedgesec/v2/model/create_domain_request_body.py
huaweicloudsdkedgesec/v2/model/create_domain_response.py
huaweicloudsdkedgesec/v2/model/create_http_access_control_rule_request.py
huaweicloudsdkedgesec/v2/model/create_http_access_control_rule_request_body.py
huaweicloudsdkedgesec/v2/model/create_http_access_control_rule_response.py
huaweicloudsdkedgesec/v2/model/create_http_block_trust_ip_rule_request.py
huaweicloudsdkedgesec/v2/model/create_http_block_trust_ip_rule_request_body.py
huaweicloudsdkedgesec/v2/model/create_http_block_trust_ip_rule_response.py
huaweicloudsdkedgesec/v2/model/create_http_cc_rule_request.py
huaweicloudsdkedgesec/v2/model/create_http_cc_rule_request_body.py
huaweicloudsdkedgesec/v2/model/create_http_cc_rule_response.py
huaweicloudsdkedgesec/v2/model/create_http_geo_ip_rule_request.py
huaweicloudsdkedgesec/v2/model/create_http_geo_ip_rule_request_body.py
huaweicloudsdkedgesec/v2/model/create_http_geo_ip_rule_response.py
huaweicloudsdkedgesec/v2/model/create_http_ignore_rule_request.py
huaweicloudsdkedgesec/v2/model/create_http_ignore_rule_request_body.py
huaweicloudsdkedgesec/v2/model/create_http_ignore_rule_response.py
huaweicloudsdkedgesec/v2/model/create_http_ip_group_request.py
huaweicloudsdkedgesec/v2/model/create_http_ip_group_request_body.py
huaweicloudsdkedgesec/v2/model/create_http_ip_group_response.py
huaweicloudsdkedgesec-3.1.184.dist-info/METADATA
huaweicloudsdkedgesec-3.1.184.dist-info/WHEEL
huaweicloudsdkedgesec-3.1.184.dist-info/licenses/LICENSE
huaweicloudsdkedgesec-3.1.184.dist-info/RECORD
